[
{"title": "人民观点：把握开放与自主的辩证法", "link": "http://www.chinanews.com/gn/2019/08-07/8919173.shtml", "desc": "　　把握开放与自主的辩证法(人民观点)", "pub_date": "2019-08-07 09:47:51"},
{"title": "要不已被翻拍要不就在被翻拍的路上 翻拍经典更要创造经典", "link": "http://www.chinanews.com/yl/2019/08-07/8919172.shtml", "desc": "　　翻拍经典，更要创造经典(评论员随笔)", "pub_date": "2019-08-07 09:47:49"},
{"title": "当局：曼谷爆炸案与南部叛乱分子有关 9名嫌犯被捕", "link": "http://www.chinanews.com/gj/2019/08-07/8919168.shtml", "desc": "\n　　中新网8月7日电 综合报道，当地时间6日，泰国副总理兼国防部长巴逸表示，日前发生在曼谷的连环爆炸案与南部叛乱分子有关联。泰当局已抓获9名嫌犯，安全部门和警方正展开严格盘查，看是否还有他人参与，并查出其作案动机。", "pub_date": "2019-08-07 09:46:16"},
{"title": "美多名专家质疑美国政府将中国列为“汇率操纵国”", "link": "http://www.chinanews.com/gn/2019/08-07/8919167.shtml", "desc": "\n　　新华社华盛顿8月6日电(记者熊茂伶 刘阳)针对5日美国财政部将中国列为“汇率操纵国”的举动，多位美国专家当天表示质疑。他们认为，人民币汇率波动符合市场规律，不应受到美方责难。", "pub_date": "2019-08-07 09:45:54"},
{"title": "人民日报评论员：温暖住有所居的梦想", "link": "http://www.chinanews.com/gn/2019/08-07/8919166.shtml", "desc": "　　温暖住有所居的梦想(评论员观察)", "pub_date": "2019-08-07 09:42:30"},
{"title": "琼台两岸少数民族青年海南同台献舞共迎“七夕”", "link": "http://www.chinanews.com/tw/2019/08-07/8919113.shtml", "desc": "\n　　中新网海南保亭8月7日电 (记者 王晓斌)8月6日晚“七夕”前夜，一场大型民族歌舞晚会在海南保亭七仙广场上演，琼台两地少数民族青年轮流登台表演节目，共同迎接“七夕”的到来。", "pub_date": "2019-08-07 09:41:57"},
{"title": "报告：美国近16年开发致大自然流失 约合9个大峡谷", "link": "http://www.chinanews.com/gj/2019/08-07/8919165.shtml", "desc": "\n　　中新网8月7日电 据美国《世界日报》报道，日前，一份最新公布的报告显示，由于农业、能源开发、居住区扩张和其他人为因素，美国在2001年到2017年间，已流失相当于9个大峡谷国家公园大小的自然区域。", "pub_date": "2019-08-07 09:41:51"},
{"title": "担心令喜爱韩国的日本人不快？首尔市中区撤走反日旗", "link": "http://www.chinanews.com/gj/2019/08-07/8919162.shtml", "desc": "\n　　中新网8月7日电 据日本共同社报道，在日韩政府间对立的背景下，韩国首尔市中区6日在众多日本游客到访的闹市区街头，挂起了呼吁抵制日货的旗子，但批评此举“会令因喜爱韩国而来的日本人感到不快”的意见纷至沓来，不得不撤走了旗子。", "pub_date": "2019-08-07 09:41:04"},
{"title": "中国老百姓日子怎样越过越红火？幸福是奋斗出来的", "link": "http://www.chinanews.com/gn/2019/08-07/8919160.shtml", "desc": "　　幸福是奋斗出来的(新中国发展面对面⑤)——中国老百姓日子怎样越过越红火？", "pub_date": "2019-08-07 09:39:27"},
{"title": "南非设立中文日", "link": "http://www.chinanews.com/gj/2019/08-07/8919159.shtml", "desc": "　　南非设立中文日", "pub_date": "2019-08-07 09:39:23"},
{"title": "第二届全国青年运动会准备就绪", "link": "http://www.chinanews.com/ty/2019/08-07/8919157.shtml", "desc": "　　青春的约会 拼搏的舞台", "pub_date": "2019-08-07 09:37:14"},
{"title": "日本广岛市举行原子弹轰炸七十四周年纪念活动", "link": "http://www.chinanews.com/gj/2019/08-07/8919156.shtml", "desc": "　　日本广岛市举行原子弹轰炸七十四周年纪念活动", "pub_date": "2019-08-07 09:36:50"},
{"title": "人民币对美元汇率中间价报6.9996元 下调313个基点", "link": "http://www.chinanews.com/fortune/2019/08-07/8919153.shtml", "desc": "\n　　中新网8月7日电 据中国外汇交易中心网站消息，8月7日人民币对美元汇率中间价为6.9996元，下调313个基点。", "pub_date": "2019-08-07 09:35:33"},
{"title": "“天津男子泰国杀妻骗保案”8日再开庭 受害人父母将作证", "link": "http://www.chinanews.com/sh/2019/08-07/8919154.shtml", "desc": "\n　　“天津男子普吉岛杀妻骗保案”将于8月8日在泰国普吉府法院继续开庭审理。澎湃新闻(www.thepaper.cn)8月6日晚从被害人张英(化名)父亲张仁俭处获悉，家属已于6日中午抵达泰国，8月9日、10日和13日三天进行庭审，8日和9日由原告方证人继续出庭作证，被告张某凡将于13日做最后陈述。他和妻子暂定9日出庭，对张某凡骗保以及天津警方提交的证据作证。", "pub_date": "2019-08-07 09:34:35"},
{"title": "70城房价数据不准确？统计局原局长：不用怀疑其科学性", "link": "http://www.chinanews.com/cj/2019/08-07/8919150.shtml", "desc": "\n　　70城房价数据不准确？统计局原局长：不用怀疑它的科学性", "pub_date": "2019-08-07 09:33:41"},
{"title": "山西上半年查获侵权假冒案件2118起 罚款超千万元", "link": "http://www.chinanews.com/cj/2019/08-07/8919123.shtml", "desc": "\n　　中新网太原8月7日电(杨杰英) 记者7日从山西省市场监管局获悉，2019年上半年，山西省市场监管局执法稽查以打击侵权假冒为工作重心，不断加大执法办案力度，工作取得明显成效。全省共出动执法人员9.2万人次，查获违法案件2118起，案值1399.5万元，没收金额47.21万元，罚款金额1055.9万余元，移送司法机关案件8起，移送司法机关人数8人。", "pub_date": "2019-08-07 09:33:39"},
{"title": "上海自贸区新片区放松限购 专家：影响不会太大", "link": "http://www.chinanews.com/cj/2019/08-07/8919149.shtml", "desc": "\n　　中新经纬客户端8月6日电 (薛宇飞)国务院日前印发了《中国(上海)自由贸易试验区临港新片区总体方案》，方案提出，中国(上海)自由贸易试验区临港新片区参照经济特区管理。在打造更具吸引力的人才发展环境上，新片区降低了人才“居转户”年限，外来人口买房资格从社保或个税需要缴纳5年降至缴纳3年，取消“外地单身不能买房”禁令等。", "pub_date": "2019-08-07 09:33:07"},
{"title": "多地歌手齐聚牛郎织女文化之乡 献唱各民族情歌", "link": "http://www.chinanews.com/cul/2019/08-07/8919117.shtml", "desc": "\n　　中新网晋中8月7日电 (李庭耀)8月6日晚，七夕前夜，《我们的节日》——“爱在七夕”中国(和顺)情歌会在“中国牛郎织女文化之乡”山西和顺举行，来自湖南、广西、陕西、江西、宁夏、四川、西藏、海南、山西等多地的男女歌手同台放歌，献上各民族情歌。", "pub_date": "2019-08-07 09:32:05"},
{"title": "河北沧州：刷新大运河“颜值” 让“千年文脉”更具活力", "link": "http://www.chinanews.com/sh/2019/08-07/8919146.shtml", "desc": "\n　　新华社石家庄8月7日电(记者冯维健)“大运河是沧州的母亲河，大运河风景好了，我们沧州人脸上也有光。”从小生活在运河畔的姜永康，从未想过有一天自家门前的这条运河，也能成为网民热捧的“网红打卡地”。", "pub_date": "2019-08-07 09:30:31"},
{"title": "“电管家”专属服务 贫困县企节能省成本", "link": "http://www.chinanews.com/sh/2019/08-07/8919145.shtml", "desc": "\n　　新华社石家庄8月7日电(记者任丽颖)“过去，我们用电常常为‘功率因数’‘变压器运行方式’这些专业术语发愁，现在有了‘电管家’专属服务，既方便又节能，一年能省成本10万多元呢。”河北省新河县的华曙新能源有限公司经理郜云峰告诉记者。", "pub_date": "2019-08-07 09:29:47"},
{"title": "人民日报金社平：乱贴“汇率操纵国”标签终将自食其果", "link": "http://www.chinanews.com/cj/2019/08-07/8919143.shtml", "desc": "　　乱贴“汇率操纵国”标签终将自食其果", "pub_date": "2019-08-07 09:28:57"},
{"title": "辽宁丹东优质特色农业产业为高质量绿色发展赋能 ", "link": "http://www.chinanews.com/gn/2019/08-07/8919115.shtml", "desc": "\n　　中新网丹东8月7日电 (李晛)截至目前，辽宁丹东已建设15个优质特色农业产业基地，是全国最大的草莓、板栗生产基地；丹东东港市被评为首批国家级农产品质量安全县；农产品质量抽检合格率达到98.8%。", "pub_date": "2019-08-07 09:28:42"},
{"title": "推动立法工作不断实现新发展", "link": "http://www.chinanews.com/gn/2019/08-07/8919142.shtml", "desc": "　　推动立法工作不断实现新发展(光辉的历程 深刻的启示·庆祝新中国成立70周年)", "pub_date": "2019-08-07 09:27:43"},
{"title": "人民币汇率稳定有支撑：经济基本面良好 外汇市场平稳运行", "link": "http://www.chinanews.com/cj/2019/08-07/8919141.shtml", "desc": "　　经济基本面良好，外汇市场平稳运行——", "pub_date": "2019-08-07 09:27:41"},
{"title": "探访美国兽医医院 护理专业细致涵盖针灸水疗", "link": "http://www.chinanews.com/tp/hd2011/2019/08-07/895948.shtml", "desc": " ", "pub_date": "2019-08-07 09:27:05"},
{"title": "七夕的早班", "link": "http://www.chinanews.com/kong/2019/08-07/8919139.shtml", "desc": null, "pub_date": "2019-08-07 09:26:58"},
{"title": "西藏昌都儿童体质健康与运动促进项目在天津体育学院启动", "link": "http://www.chinanews.com/sh/2019/08-07/8919114.shtml", "desc": "\n　　中新网天津8月7日电 (记者 张道正)中央财政支持社会组织示范项目——西藏昌都儿童体质健康与运动促进启动暨天津援藏干部低氧与运动健康促进中心揭牌仪式，6日在天津体育学院举行。", "pub_date": "2019-08-07 09:26:48"},
{"title": "人民时评：激活家访的育人效能", "link": "http://www.chinanews.com/gn/2019/08-07/8919138.shtml", "desc": "　　激活家访的育人效能(人民时评)", "pub_date": "2019-08-07 09:25:50"},
{"title": "国家电影局：暂停大陆影片和人员参加2019年金马影展", "link": "http://www.chinanews.com/yl/2019/08-07/8919137.shtml", "desc": "\n　　国家电影局消息，暂停大陆影片和人员参加2019年第56届台北金马影展。(记者白瀛) #8203;#8203;#8203;#8203;", "pub_date": "2019-08-07 09:25:32"},
{"title": "谱写依宪治国精彩篇章", "link": "http://www.chinanews.com/gn/2019/08-07/8919134.shtml", "desc": "　　谱写依宪治国精彩篇章(大家手笔)", "pub_date": "2019-08-07 09:23:58"}
]